MANIFEST.in
README.rst
requirements.txt
setup.py
test_requirements.txt
django_trees/__init__.py
django_trees/exceptions.py
django_trees/managers.py
django_trees/models.py
django_trees/signals.py
django_trees.egg-info/PKG-INFO
django_trees.egg-info/SOURCES.txt
django_trees.egg-info/dependency_links.txt
django_trees.egg-info/requires.txt
django_trees.egg-info/top_level.txt
django_trees/tests/__init__.py
django_trees/tests/ascii_tree_tests.py
django_trees/tests/branched_tree_tests.py
django_trees/tests/helper.py
django_trees/tests/multiple_tree_tests.py
django_trees/tests/straight_tree_tests.py
django_trees/tests/test_app/__init__.py
django_trees/tests/test_app/models.py