Metadata-Version: 1.1
Name: django-trees
Version: 2.0.1
Summary: Simple way to create, persist and manipulate reliable tree structures using Django models.
Home-page: https://github.com/imtapps/django_trees
Author: imtapps
Author-email: serveradmin@imtapps.com
License: UNKNOWN
Platform: UNKNOWN
Classifier: Development Status :: 5 - Production/Stable
Classifier: Framework :: Django
Classifier: Environment :: Web Environment
Classifier: License :: OSI Approved :: MIT License
Classifier: Programming Language :: Python
Classifier: Programming Language :: Python :: 2.7
Classifier: Topic :: Database
Classifier: Topic :: Software Development :: Libraries
